yt_dlp_plugins/extractor/getpot_bgutil.py
definitely_not_bgutil_ytdlp_pot_provider_to_distinguish_from_it-0.2.29.dist-info/METADATA
definitely_not_bgutil_ytdlp_pot_provider_to_distinguish_from_it-0.2.29.dist-info/WHEEL
definitely_not_bgutil_ytdlp_pot_provider_to_distinguish_from_it-0.2.29.dist-info/RECORD
