Metadata-Version: 2.3
Name: definitely_not_bgutil-ytdlp-pot-provider_to_distinguish_from_it
Version: 0.2.29
Author-email: Brainicism <brainicism@gmail.com>
Keywords: yt-dlp,yt-dlp-plugin
Requires-Python: >=3.8
Requires-Dist: yt-dlp-get-pot>=0.0.2
